{"filename":"d:\\upwork\\azure_func\\__azurite_db_blob_extent__.json","collections":[{"name":"$EXTENTS_COLLECTION$","data":[{"id":"b8d2cf4d-53cc-4db8-8201-83e522878a65","locationId":"Default","path":"b8d2cf4d-53cc-4db8-8201-83e522878a65","size":373,"lastModifiedInMS":1627752209948,"meta":{"revision":4,"created":1627752209949,"version":0,"updated":1627752619462},"$loki":1,"LastModifyInMS":1627752619462},{"id":"3ffc9410-caaf-487c-9ca7-482b1ed4acb4","locationId":"Default","path":"3ffc9410-caaf-487c-9ca7-482b1ed4acb4","size":258,"lastModifiedInMS":1628333846814,"meta":{"revision":1,"created":1628333846818,"version":0,"updated":1628334081215},"$loki":7,"LastModifyInMS":1628334081214}],"idIndex":[1,7],"binaryIndices":{"id":{"name":"id","dirty":false,"values":[1,0]}},"constraints":null,"uniqueNames":[],"transforms":{},"objType":"$EXTENTS_COLLECTION$","dirty":false,"cachedIndex":null,"cachedBinaryIndex":null,"cachedData":null,"adaptiveBinaryIndices":true,"transactional":false,"cloneObjects":false,"cloneMethod":"parse-stringify","asyncListeners":false,"disableMeta":false,"disableChangesApi":true,"disableDeltaChangesApi":true,"autoupdate":false,"serializableIndices":true,"disableFreeze":true,"ttl":null,"maxId":7,"DynamicViews":[],"events":{"insert":[],"update":[],"pre-insert":[],"pre-update":[],"close":[],"flushbuffer":[],"error":[],"delete":[null],"warning":[null]},"changes":[],"dirtyIds":[]}],"databaseVersion":1.5,"engineVersion":1.5,"autosave":true,"autosaveInterval":5000,"autosaveHandle":null,"throttledSaves":true,"options":{"autosave":true,"autosaveInterval":5000,"serializationMethod":"normal","destructureDelimiter":"$<\n"},"persistenceMethod":"fs","persistenceAdapter":null,"verbose":false,"events":{"init":[null],"loaded":[],"flushChanges":[],"close":[],"changes":[],"warning":[]},"ENV":"NODEJS"}